cbsel.v
`include "sw.vh"
module cbsel(input [`PKTW:0] i0, i1, i2, i3, output [`PKTW:0] o, input [`PORT:0] d);
    reg o;

//create cbsel0-3 

//d0 = {ack03, ack02, ack01, ack00}
//d1 = {ack13, ack12, ack11, ack10}
//d2 = {ack23, ack22, ack21, ack20}
//d3 = {ack33, ack32, ack31, ack30}

    always_comb begin
        if(d[0]) o = i0;  
        else if(d[1]) o = i1;
        else if(d[2]) o = i2;
        else if(d[3]) o = i3;
        else o = 0;
    end
endmodule

cb.v
`include "sw.vh"
module cb(input [`PKTW:0] i0, i1, i2, i3, output [`PKTW:0] o0, o1, o2, o3,
    input [`PORT:0] d0, d1, d2, d3);

//d0 = {ack03, ack02, ack01, ack00}
//d1 = {ack13, ack12, ack11, ack10}
//d2 = {ack23, ack22, ack21, ack20}
//d3 = {ack33, ack32, ack31, ack30}

    cbsel cbsel0(i0, i1, i2, i3, o0, d0); 
    cbsel cbsel1(i0, i1, i2, i3, o1, d1);
    cbsel cbsel2(i0, i1, i2, i3, o2, d2);
    cbsel cbsel3(i0, i1, i2, i3, o3, d3);
endmodule

arb.v
`include "sw.vh"
module arb(input req0, req1, req2, req3, output ackx0, ackx1, ackx2, ackx3, input clk, rst);

//req0[1] from 0 to 1
//create arb 0-3
/*
    if(req0 == 1) ackx0 <= 1;
    if(req1 == 1) ackx1 <= 1;
    if(req2 == 1) ackx2 <= 1;
    if(req3 == 1) ackx3 <= 1;
*/
    logic turn = 0;
    logic ackx0, ackx1, ackx2, ackx3;

    always @(posedge clk) begin
        if(rst) begin
            turn <= 0;
            ackx0 <= `NEGATE;
            ackx1 <= `NEGATE;
            ackx2 <= `NEGATE;
            ackx3 <= `NEGATE;
        end

        /*
        if(ack00 == 0 && ack10 == 0 && ack20 == 0 && ack30 == 0)  o0 <= 0;  // all 0
        else if(ack00 == 1 && ack10 == 0 && ack20 == 0 && ack30 == 0) o0 <= co0; // without competition
        else if(ack00 == 0 && ack10 == 1 && ack20 == 0 && ack30 == 0) o0 <= co1;
        else if(ack00 == 0 && ack10 == 0 && ack20 == 1 && ack30 == 0) o0 <= co2;
        else if(ack00 == 0 && ack10 == 0 && ack20 == 0 && ack30 == 1) o0 <= co3;
        else begin 
            */
        ackx0 <= `NEGATE;
        ackx1 <= `NEGATE;
        ackx2 <= `NEGATE;
        ackx3 <= `NEGATE;
        case (turn)
            0: begin  //from port 0
                if(req0) ackx0 <= `ASSERT;   //want to send to port 0
                else if(req1) ackx1 <= `ASSERT;
                else if(req2) ackx2 <= `ASSERT;
                else if(req3) ackx3 <= `ASSERT;
                else turn = turn + 1;
            end
            1: begin  //from port 1
                if(req0) ackx0 <= `ASSERT;   //want to send to port 0
                else if(req1) ackx1 <= `ASSERT;
                else if(req2) ackx2 <= `ASSERT;
                else if(req3) ackx3 <= `ASSERT;
                else turn = turn + 1;
            end
            2: begin  //from port 2
                if(req0) ackx0 <= `ASSERT;   //want to send to port 0
                else if(req1) ackx1 <= `ASSERT;
                else if(req2) ackx2 <= `ASSERT;
                else if(req3) ackx3 <= `ASSERT;
                else turn = turn + 1;
            end
            3: begin  //from port 3
                if(req0) ackx0 <= `ASSERT;   //want to send to port 0
                else if(req1) ackx1 <= `ASSERT;
                else if(req2) ackx2 <= `ASSERT;
                else if(req3) ackx3 <= `ASSERT;
                else turn = 0;
            end
        endcase
    end

/*
                if(next0 == 0) begin
                    
                    o0 <= co0;  // from 0
                    if(co0[9:8] == `TAIL) begin // after sending the chunk of packet0
                        o0 <= co0;
                        next0 == 1; 
                    end
                end
                if(next0 == 1) begin 
                    o0 <= co1;  // from 1
                    if(co1[9:8] == `TAIL) begin
                        o0 <= co1;
                        next1 == 1; 
                        next0 == 0;
                    end
                end
                if(next1 == 1) begin
                    o0 <= co2;
                    if(co2[9:8] == `TAIL) begin
                        o0 <= co2;
                        next2 == 1;
                        next1 == 0;
                    end
                end
                if(next2 == 1) begin
                    o0 <= co3;
                    if(co3[9:8] == `TAIL) begin
                        o0 <= co3;
                        next2 == 0;
                    end
                end
                
            end
            */
endmodule

ackor.v
`include "sw.vh"
module ackor(input ack0x, ack1x, ack2x, ack3x, output ack);
  
    assign ack = ack0x | ack1x | ack2x | ack3x;

endmodule

ibsm.v
`include "sw.vh"
module ibsm(input [`PORT:0] reqi, input [`PKTW:0] pout, input empty, input ack, input clk, rst, output [`PORT:0] req, output re);
    logic re;
    reg req;

    logic [1:0] state;
    logic [1:0] nstate;
    //state 00 : before sending req
    //state 01 : waiting ack
    //state 10 : sending packet
    //state 11 : finished

    always @(posedge clk) begin
        if(rst) begin
        re <= 0;
        req <= 4'b0000;
        state <= 0;
        end else begin
            if(reqi != 0) req <= reqi; 
            if(pout[`FLOWBH:`FLOWBL] == `TAIL) req <= 0;

            state <= nstate;
/*
            if(state == 2'b00) begin
                if(reqi != 0) begin
                    req <= reqi; 
                end
                if(pout[`FLOWBH:`FLOWBL] == `TAIL) req <= 0;
            end

            if(state == 2'b01) begin
                req <= 0;
            end

            if(state == 2'b10) begin
                
            end
            */
        end
    end

 
    always_comb begin
        if(state == 2'b00) begin
            re = 0;
            if(req != 0) nstate = 2'b01;
            else nstate = 2'b00;
        end

        if(state == 2'b01) begin
            if(ack) begin
                if(empty) begin
                    nstate = 2'b11;
                    re = 0;
                end
                else begin
                    nstate = 2'b10;
                    re = 1;
                end
            end else begin
                nstate = 2'b01;
                re = 0;
            end
        end
        if(state == 2'b10) begin
            if(empty || pout[`FLOWBH:`FLOWBL] == `TAIL) begin
                re = 0;
                nstate = 2'b11;
            end
            else begin
                re = 1;
                nstate = 2'b10;
            end
        end
        if(state == 2'b11) begin
            nstate = 2'b00;
            re = 1;
        end
    end

endmodule

mkreq.v
`include "sw.vh"
module mkreq(input [`PKTW:0] pkti, output [`PORT:0] req, input clk, rst);
    logic [`PORT:0] req;
    always@ (posedge clk) begin
        if(rst) req <= 4'b0000;
        else if(pkti[`FLOWBH:`FLOWBL] == `HEAD) begin   // if header
            case(pkti[1:0]) // create reqest depending on the destination
                2'b00: req <= 4'b0001;
                2'b01: req <= 4'b0010;
                2'b10: req <= 4'b0100;
                2'b11: req <= 4'b1000;
            endcase
        end else if(pkti[`FLOWBH:`FLOWBL] == `EMPT) begin
            req <= 4'b0000;
        end else if(pkti[`FLOWBH:`FLOWBL] == `TAIL) begin
            req <= 4'b0000;
        end

    end
endmodule

mkwe.v
`include "sw.vh"
module mkwe(input [`PKTW:0] pkti, output we);
    logic we;
    always_comb begin
        if(pkti[`FLOWBH:`FLOWBL] != `EMPT) we = `ASSERT; // if no data
        else we = `NEGATE;
    end
endmodule

fifo.v
`include "sw.vh"
module fifo(input [`PKTW:0] in, input we, output logic full,
	output [`PKTW:0] out, input re, output logic empty, input clk, rst);
	logic [`FIFOLB:0] head, tail, headi;
	logic [`PKTW:0] mem [`FIFOL:0];
	logic [`PKTW:0] out;

	//assign out = mem[tail]; 
	always @(posedge clk) if(we) mem[head] <= in;
	assign headi = head + 1;
	always @(posedge clk) begin
		if(rst) begin
			head <= 0;
			tail <= 0;
		end else begin
			if(we) head <= headi;
			if(re) tail <= tail + 1;
		end
	end
	always_comb begin
		if(head == tail) begin
			empty = 1'b1;
			out = 0;
		end
		else begin
			empty = 1'b0;
			out = mem[tail];
		end
		//if(empty) out <= 0;
		if(headi == tail) full = 1'b1;
		else full = 1'b0;
	end
endmodule

ib.v
`include "sw.vh"
//module ib(input [`PKTW:0] pkti, output [`PKTW:0] pkto, [`PORT:0] req, input ack, output full, input clk, rst);

module ib(input [`PKTW:0] pkti, output [`PKTW:0] pkto, output [`PORT:0] req, input ack, output full, input clk, rst);

    //logic [`PKTW:0] pkti;
    logic [`PORT:0] reqi;
    //mkwe mkwe(pkti, we);
    fifo fifo(pkti, we, full, pkto, re, empty, clk, rst);
    mkwe mkwe(pkti, we);
    mkreq mkreq(pkto, reqi, clk, rst);
    ibsm ibsm(reqi, pkto, empty, ack, clk, rst, req, re);
endmodule

sw.v
`include "sw.vh"
module sw(input [`PKTW:0] i0, i1, i2, i3, output [`PKTW:0] o0, o1, o2, o3, input clk, rst);
	logic [`PKTW:0] co0, co1, co2, co3;
	logic [`PORT:0] req0, req1, req2, req3;
	ib ib0(i0, co0, req0, ack0, full0, clk, rst);  
	ib ib1(i1, co1, req1, ack1, full1, clk, rst);
	ib ib2(i2, co2, req2, ack2, full2, clk, rst);
	ib ib3(i3, co3, req3, ack3, full3, clk, rst);
	ackor ackor0(ack00, ack10, ack20, ack30, ack0);
	ackor ackor1(ack01, ack11, ack21, ack31, ack1);
	ackor ackor2(ack02, ack12, ack22, ack32, ack2);
	ackor ackor3(ack03, ack13, ack23, ack33, ack3);
	arb arb0(req0[0], req1[0], req2[0], req3[0], ack00, ack01, ack02, ack03, clk, rst); // from port 0 
	arb arb1(req0[1], req1[1], req2[1], req3[1], ack10, ack11, ack12, ack13, clk, rst); // from port 1
	arb arb2(req0[2], req1[2], req2[2], req3[2], ack20, ack21, ack22, ack23, clk, rst); // from port 2
	arb arb3(req0[3], req1[3], req2[3], req3[3], ack30, ack31, ack32, ack33, clk, rst); // from port 3
	cb cb(co0, co1, co2, co3, o0, o1, o2, o3,
		{ack03, ack02, ack01, ack00}, {ack13, ack12, ack11, ack10},
		{ack23, ack22, ack21, ack20}, {ack33, ack32, ack31, ack30});
endmodule

swtest.v
`include "sw.vh"
module swtest;
	logic [`PKTW:0] i0, i1, i2, i3;
	logic [`PKTW:0] o0, o1, o2, o3;
	logic clk, rst;
	sw sw(i0, i1, i2, i3, o0, o1, o2, o3, clk, rst);
	always #5 clk = ~clk;
initial begin
$dumpfile("sw.vcd");
$dumpvars(0, swtest);
clk = 0;
i0 = 0;
i1 = 0;
i2 = 0;
i3 = 0;
rst = `ASSERT;
#10
rst = `NEGATE;
#10
i0 = 10'b10_0000_0000; // port0 => port0 length 4   //開始　＋　行先
#10
i0 = 10'b01_0000_0000;
#10
i0 = 10'b01_0000_0001;
#10
i0 = 10'b11_0000_0010; //終了
#10
i0 = 0;
#10
i0 = 10'b10_1001_0001; // port0 => port1 length 4
#10
i0 = 10'b01_1001_0000;
#10
i0 = 10'b01_1001_0001;
#10
i0 = 10'b11_1001_0010;
#10
i0 = 0;
#10
i0 = 10'b10_0000_0000; // port0 => port0 short
#10
i0 = 10'b11_0000_1111;
#10
i0 = 10'b10_0000_0001; // port0 => port1 short
#10
i0 = 10'b11_0000_1111;
#10
i0 = 10'b10_0000_0010; // port0 => port2 short
#10
i0 = 10'b11_0000_1111;
#10
i0 = 10'b10_0000_0011; // port0 => port3 short
#10
i0 = 10'b11_0000_1111;
#10
i0 = 0;
#10
i1 = 10'b10_0001_0000; // port1 => port0 short
#10
i1 = 10'b11_0001_1111;
#10
i1 = 10'b10_0001_0001; // port1 => port1 short
#10
i1 = 10'b11_0001_1111;
#10
i1 = 10'b10_0001_0010; // port1 => port2 short
#10
i1 = 10'b11_0001_1111;
#10
i1 = 10'b10_0001_0011; // port1 => port3 short
#10
i1 = 10'b11_0001_1111;
#10
i1 = 0;
#10
i2 = 10'b10_0010_0000; // port2 => port0 short
#10
i2 = 10'b11_0010_1111;
#10
i2 = 10'b10_0010_0001; // port2 => port1 short
#10
i2 = 10'b11_0010_1111;
#10
i2 = 10'b10_0010_0010; // port2 => port2 short
#10
i2 = 10'b11_0010_1111;
#10
i2 = 10'b10_0010_0011; // port2 => port3 short
#10
i2 = 10'b11_0010_1111;
#10
i2 = 0;
#10
i3 = 10'b10_0011_0000; // port3 => port0 short
#10
i3 = 10'b11_0011_1111;
#10
i3 = 10'b10_0011_0001; // port3 => port1 short
#10
i3 = 10'b11_0011_1111;
#10
i3 = 10'b10_0011_0010; // port3 => port2 short
#10
i3 = 10'b11_0011_1111;
#10
i3 = 10'b10_0011_0011; // port3 => port3 short
#10
i3 = 10'b11_0011_1111;
#10
i3 = 0;
#100
i0 = 10'b10_0000_0001; // port0 => port1 length 4 conflict
i1 = 10'b10_0001_0001; // port0 => port1 length 4 conflict
i2 = 10'b10_0010_0001; // port0 => port1 length 4 conflict
i3 = 10'b10_0011_0001; // port0 => port1 length 4 conflict
#10
i0 = 10'b01_0000_0000;
i1 = 10'b01_0001_0000;
i2 = 10'b01_0010_0000;
i3 = 10'b01_0011_0000;
#10
i0 = 10'b01_0000_0001;
i1 = 10'b01_0001_0001;
i2 = 10'b01_0010_0001;
i3 = 10'b01_0011_0001;
#10
i0 = 10'b11_0000_1111;
i1 = 10'b11_0001_1111;
i2 = 10'b11_0010_1111;
i3 = 10'b11_0011_1111;
#10
i0 = 0;
i1 = 0;
i2 = 0;
i3 = 0;
#200
i0 = 10'b10_0000_0000; // port0 => port0 short conflict
i1 = 10'b10_0001_0000; // port0 => port0 short conflict
i2 = 10'b10_0010_0000; // port0 => port0 short conflict
i3 = 10'b10_0011_0000; // port0 => port0 short conflict
#10
i0 = 10'b11_0000_1111;
i1 = 10'b11_0001_1111;
i2 = 10'b11_0010_1111;
i3 = 10'b11_0011_1111;
#10
i0 = 0;
i1 = 0;
i2 = 0;
i3 = 0;
#200
i0 = 10'b10_0000_0001; // port0 => port1 short conflict
i1 = 10'b10_0001_0001; // port0 => port1 short conflict
i2 = 10'b10_0010_0001; // port0 => port1 short conflict
i3 = 10'b10_0011_0001; // port0 => port1 short conflict
#10
i0 = 10'b11_0000_1111;
i1 = 10'b11_0001_1111;
i2 = 10'b11_0010_1111;
i3 = 10'b11_0011_1111;
#10
i0 = 0;
i1 = 0;
i2 = 0;
i3 = 0;
#200
i0 = 10'b10_0000_0010; // port0 => port2 short conflict
i1 = 10'b10_0001_0010; // port0 => port2 short conflict
i2 = 10'b10_0010_0010; // port0 => port2 short conflict
i3 = 10'b10_0011_0010; // port0 => port2 short conflict
#10
i0 = 10'b11_0000_1111;
i1 = 10'b11_0001_1111;
i2 = 10'b11_0010_1111;
i3 = 10'b11_0011_1111;
#10
i0 = 0;
i1 = 0;
i2 = 0;
i3 = 0;
#200
i0 = 10'b10_0000_0011; // port0 => port3 short conflict
i1 = 10'b10_0001_0011; // port0 => port3 short conflict
i2 = 10'b10_0010_0011; // port0 => port3 short conflict
i3 = 10'b10_0011_0011; // port0 => port3 short conflict
#10
i0 = 10'b11_0000_1111;
i1 = 10'b11_0001_1111;
i2 = 10'b11_0010_1111;
i3 = 10'b11_0011_1111;
#10
i0 = 0;
i1 = 0;
i2 = 0;
i3 = 0;
#500
$finish;
end
endmodule

sw.vcd
$date
	Mon Jul 13 22:00:33 2020
$end
$version
	Icarus Verilog
$end
$timescale
	1s
$end
$scope module swtest $end
$var wire 10 ! o3 [9:0] $end
$var wire 10 " o2 [9:0] $end
$var wire 10 # o1 [9:0] $end
$var wire 10 $ o0 [9:0] $end
$var reg 1 % clk $end
$var reg 10 & i0 [9:0] $end
$var reg 10 ' i1 [9:0] $end
$var reg 10 ( i2 [9:0] $end
$var reg 10 ) i3 [9:0] $end
$var reg 1 * rst $end
$scope module sw $end
$var wire 1 % clk $end
$var wire 10 + i0 [9:0] $end
$var wire 10 , i1 [9:0] $end
$var wire 10 - i2 [9:0] $end
$var wire 10 . i3 [9:0] $end
$var wire 1 * rst $end
$var wire 4 / req3 [3:0] $end
$var wire 4 0 req2 [3:0] $end
$var wire 4 1 req1 [3:0] $end
$var wire 4 2 req0 [3:0] $end
$var wire 10 3 o3 [9:0] $end
$var wire 10 4 o2 [9:0] $end
$var wire 10 5 o1 [9:0] $end
$var wire 10 6 o0 [9:0] $end
$var wire 1 7 full3 $end
$var wire 1 8 full2 $end
$var wire 1 9 full1 $end
$var wire 1 : full0 $end
$var wire 10 ; co3 [9:0] $end
$var wire 10 < co2 [9:0] $end
$var wire 10 = co1 [9:0] $end
$var wire 10 > co0 [9:0] $end
$var wire 1 ? ack33 $end
$var wire 1 @ ack32 $end
$var wire 1 A ack31 $end
$var wire 1 B ack30 $end
$var wire 1 C ack3 $end
$var wire 1 D ack23 $end
$var wire 1 E ack22 $end
$var wire 1 F ack21 $end
$var wire 1 G ack20 $end
$var wire 1 H ack2 $end
$var wire 1 I ack13 $end
$var wire 1 J ack12 $end
$var wire 1 K ack11 $end
$var wire 1 L ack10 $end
$var wire 1 M ack1 $end
$var wire 1 N ack03 $end
$var wire 1 O ack02 $end
$var wire 1 P ack01 $end
$var wire 1 Q ack00 $end
$var wire 1 R ack0 $end
$scope module ackor0 $end
$var wire 1 R ack $end
$var wire 1 B ack3x $end
$var wire 1 G ack2x $end
$var wire 1 L ack1x $end
$var wire 1 Q ack0x $end
$upscope $end
$scope module ackor1 $end
$var wire 1 M ack $end
$var wire 1 A ack3x $end
$var wire 1 F ack2x $end
$var wire 1 K ack1x $end
$var wire 1 P ack0x $end
$upscope $end
$scope module ackor2 $end
$var wire 1 H ack $end
$var wire 1 @ ack3x $end
$var wire 1 E ack2x $end
$var wire 1 J ack1x $end
$var wire 1 O ack0x $end
$upscope $end
$scope module ackor3 $end
$var wire 1 C ack $end
$var wire 1 ? ack3x $end
$var wire 1 D ack2x $end
$var wire 1 I ack1x $end
$var wire 1 N ack0x $end
$upscope $end
$scope module arb0 $end
$var wire 1 % clk $end
$var wire 1 S req0 $end
$var wire 1 T req1 $end
$var wire 1 U req2 $end
$var wire 1 V req3 $end
$var wire 1 * rst $end
$var reg 1 Q ackx0 $end
$var reg 1 P ackx1 $end
$var reg 1 O ackx2 $end
$var reg 1 N ackx3 $end
$var reg 1 W turn $end
$upscope $end
$scope module arb1 $end
$var wire 1 % clk $end
$var wire 1 X req0 $end
$var wire 1 Y req1 $end
$var wire 1 Z req2 $end
$var wire 1 [ req3 $end
$var wire 1 * rst $end
$var reg 1 L ackx0 $end
$var reg 1 K ackx1 $end
$var reg 1 J ackx2 $end
$var reg 1 I ackx3 $end
$var reg 1 \ turn $end
$upscope $end
$scope module arb2 $end
$var wire 1 % clk $end
$var wire 1 ] req0 $end
$var wire 1 ^ req1 $end
$var wire 1 _ req2 $end
$var wire 1 ` req3 $end
$var wire 1 * rst $end
$var reg 1 G ackx0 $end
$var reg 1 F ackx1 $end
$var reg 1 E ackx2 $end
$var reg 1 D ackx3 $end
$var reg 1 a turn $end
$upscope $end
$scope module arb3 $end
$var wire 1 % clk $end
$var wire 1 b req0 $end
$var wire 1 c req1 $end
$var wire 1 d req2 $end
$var wire 1 e req3 $end
$var wire 1 * rst $end
$var reg 1 B ackx0 $end
$var reg 1 A ackx1 $end
$var reg 1 @ ackx2 $end
$var reg 1 ? ackx3 $end
$var reg 1 f turn $end
$upscope $end
$scope module cb $end
$var wire 4 g d0 [3:0] $end
$var wire 4 h d1 [3:0] $end
$var wire 4 i d2 [3:0] $end
$var wire 4 j d3 [3:0] $end
$var wire 10 k o3 [9:0] $end
$var wire 10 l o2 [9:0] $end
$var wire 10 m o1 [9:0] $end
$var wire 10 n o0 [9:0] $end
$var wire 10 o i3 [9:0] $end
$var wire 10 p i2 [9:0] $end
$var wire 10 q i1 [9:0] $end
$var wire 10 r i0 [9:0] $end
$scope module cbsel0 $end
$var wire 4 s d [3:0] $end
$var wire 10 t i3 [9:0] $end
$var wire 10 u i2 [9:0] $end
$var wire 10 v i1 [9:0] $end
$var wire 10 w i0 [9:0] $end
$var reg 10 x o [9:0] $end
$upscope $end
$scope module cbsel1 $end
$var wire 4 y d [3:0] $end
$var wire 10 z i3 [9:0] $end
$var wire 10 { i2 [9:0] $end
$var wire 10 | i1 [9:0] $end
$var wire 10 } i0 [9:0] $end
$var reg 10 ~ o [9:0] $end
$upscope $end
$scope module cbsel2 $end
$var wire 4 !" d [3:0] $end
$var wire 10 "" i3 [9:0] $end
$var wire 10 #" i2 [9:0] $end
$var wire 10 $" i1 [9:0] $end
$var wire 10 %" i0 [9:0] $end
$var reg 10 &" o [9:0] $end
$upscope $end
$scope module cbsel3 $end
$var wire 4 '" d [3:0] $end
$var wire 10 (" i3 [9:0] $end
$var wire 10 )" i2 [9:0] $end
$var wire 10 *" i1 [9:0] $end
$var wire 10 +" i0 [9:0] $end
$var reg 10 ," o [9:0] $end
$upscope $end
$upscope $end
$scope module ib0 $end
$var wire 1 R ack $end
$var wire 1 % clk $end
$var wire 10 -" pkti [9:0] $end
$var wire 1 * rst $end
$var wire 1 ." we $end
$var wire 4 /" reqi [3:0] $end
$var wire 4 0" req [3:0] $end
$var wire 1 1" re $end
$var wire 10 2" pkto [9:0] $end
$var wire 1 : full $end
$var wire 1 3" empty $end
$scope module fifo $end
$var wire 1 % clk $end
$var wire 10 4" in [9:0] $end
$var wire 1 * rst $end
$var wire 1 ." we $end
$var wire 1 1" re $end
$var wire 4 5" headi [3:0] $end
$var reg 1 3" empty $end
$var reg 1 : full $end
$var reg 4 6" head [3:0] $end
$var reg 10 7" out [9:0] $end
$var reg 4 8" tail [3:0] $end
$upscope $end
$scope module ibsm $end
$var wire 1 R ack $end
$var wire 1 % clk $end
$var wire 1 3" empty $end
$var wire 10 9" pout [9:0] $end
$var wire 1 * rst $end
$var wire 4 :" reqi [3:0] $end
$var reg 2 ;" nstate [1:0] $end
$var reg 1 1" re $end
$var reg 4 <" req [3:0] $end
$var reg 2 =" state [1:0] $end
$upscope $end
$scope module mkreq $end
$var wire 1 % clk $end
$var wire 10 >" pkti [9:0] $end
$var wire 1 * rst $end
$var reg 4 ?" req [3:0] $end
$upscope $end
$scope module mkwe $end
$var wire 10 @" pkti [9:0] $end
$var reg 1 ." we $end
$upscope $end
$upscope $end
$scope module ib1 $end
$var wire 1 M ack $end
$var wire 1 % clk $end
$var wire 10 A" pkti [9:0] $end
$var wire 1 * rst $end
$var wire 1 B" we $end
$var wire 4 C" reqi [3:0] $end
$var wire 4 D" req [3:0] $end
$var wire 1 E" re $end
$var wire 10 F" pkto [9:0] $end
$var wire 1 9 full $end
$var wire 1 G" empty $end
$scope module fifo $end
$var wire 1 % clk $end
$var wire 10 H" in [9:0] $end
$var wire 1 * rst $end
$var wire 1 B" we $end
$var wire 1 E" re $end
$var wire 4 I" headi [3:0] $end
$var reg 1 G" empty $end
$var reg 1 9 full $end
$var reg 4 J" head [3:0] $end
$var reg 10 K" out [9:0] $end
$var reg 4 L" tail [3:0] $end
$upscope $end
$scope module ibsm $end
$var wire 1 M ack $end
$var wire 1 % clk $end
$var wire 1 G" empty $end
$var wire 10 M" pout [9:0] $end
$var wire 1 * rst $end
$var wire 4 N" reqi [3:0] $end
$var reg 2 O" nstate [1:0] $end
$var reg 1 E" re $end
$var reg 4 P" req [3:0] $end
$var reg 2 Q" state [1:0] $end
$upscope $end
$scope module mkreq $end
$var wire 1 % clk $end
$var wire 10 R" pkti [9:0] $end
$var wire 1 * rst $end
$var reg 4 S" req [3:0] $end
$upscope $end
$scope module mkwe $end
$var wire 10 T" pkti [9:0] $end
$var reg 1 B" we $end
$upscope $end
$upscope $end
$scope module ib2 $end
$var wire 1 H ack $end
$var wire 1 % clk $end
$var wire 10 U" pkti [9:0] $end
$var wire 1 * rst $end
$var wire 1 V" we $end
$var wire 4 W" reqi [3:0] $end
$var wire 4 X" req [3:0] $end
$var wire 1 Y" re $end
$var wire 10 Z" pkto [9:0] $end
$var wire 1 8 full $end
$var wire 1 [" empty $end
$scope module fifo $end
$var wire 1 % clk $end
$var wire 10 \" in [9:0] $end
$var wire 1 * rst $end
$var wire 1 V" we $end
$var wire 1 Y" re $end
$var wire 4 ]" headi [3:0] $end
$var reg 1 [" empty $end
$var reg 1 8 full $end
$var reg 4 ^" head [3:0] $end
$var reg 10 _" out [9:0] $end
$var reg 4 `" tail [3:0] $end
$upscope $end
$scope module ibsm $end
$var wire 1 H ack $end
$var wire 1 % clk $end
$var wire 1 [" empty $end
$var wire 10 a" pout [9:0] $end
$var wire 1 * rst $end
$var wire 4 b" reqi [3:0] $end
$var reg 2 c" nstate [1:0] $end
$var reg 1 Y" re $end
$var reg 4 d" req [3:0] $end
$var reg 2 e" state [1:0] $end
$upscope $end
$scope module mkreq $end
$var wire 1 % clk $end
$var wire 10 f" pkti [9:0] $end
$var wire 1 * rst $end
$var reg 4 g" req [3:0] $end
$upscope $end
$scope module mkwe $end
$var wire 10 h" pkti [9:0] $end
$var reg 1 V" we $end
$upscope $end
$upscope $end
$scope module ib3 $end
$var wire 1 C ack $end
$var wire 1 % clk $end
$var wire 10 i" pkti [9:0] $end
$var wire 1 * rst $end
$var wire 1 j" we $end
$var wire 4 k" reqi [3:0] $end
$var wire 4 l" req [3:0] $end
$var wire 1 m" re $end
$var wire 10 n" pkto [9:0] $end
$var wire 1 7 full $end
$var wire 1 o" empty $end
$scope module fifo $end
$var wire 1 % clk $end
$var wire 10 p" in [9:0] $end
$var wire 1 * rst $end
$var wire 1 j" we $end
$var wire 1 m" re $end
$var wire 4 q" headi [3:0] $end
$var reg 1 o" empty $end
$var reg 1 7 full $end
$var reg 4 r" head [3:0] $end
$var reg 10 s" out [9:0] $end
$var reg 4 t" tail [3:0] $end
$upscope $end
$scope module ibsm $end
$var wire 1 C ack $end
$var wire 1 % clk $end
$var wire 1 o" empty $end
$var wire 10 u" pout [9:0] $end
$var wire 1 * rst $end
$var wire 4 v" reqi [3:0] $end
$var reg 2 w" nstate [1:0] $end
$var reg 1 m" re $end
$var reg 4 x" req [3:0] $end
$var reg 2 y" state [1:0] $end
$upscope $end
$scope module mkreq $end
$var wire 1 % clk $end
$var wire 10 z" pkti [9:0] $end
$var wire 1 * rst $end
$var reg 4 {" req [3:0] $end
$upscope $end
$scope module mkwe $end
$var wire 10 |" pkti [9:0] $end
$var reg 1 j" we $end
$upscope $end
$upscope $end
$upscope $end
$upscope $end
$enddefinitions $end
#0
$dumpvars
b0 |"
bx {"
bx z"
bx y"
bx x"
bx w"
bx v"
bx u"
bx t"
bx s"
bx r"
bx q"
b0 p"
0o"
bx n"
xm"
bx l"
bx k"
0j"
b0 i"
b0 h"
bx g"
bx f"
bx e"
bx d"
bx c"
bx b"
bx a"
bx `"
bx _"
bx ^"
bx ]"
b0 \"
0["
bx Z"
xY"
bx X"
bx W"
0V"
b0 U"
b0 T"
bx S"
bx R"
bx Q"
bx P"
bx O"
bx N"
bx M"
bx L"
bx K"
bx J"
bx I"
b0 H"
0G"
bx F"
xE"
bx D"
bx C"
0B"
b0 A"
b0 @"
bx ?"
bx >"
bx ="
bx <"
bx ;"
bx :"
bx 9"
bx 8"
bx 7"
bx 6"
bx 5"
b0 4"
03"
bx 2"
x1"
bx 0"
bx /"
0."
b0 -"
b0 ,"
bx +"
bx *"
bx )"
bx ("
bx '"
b0 &"
bx %"
bx $"
bx #"
bx ""
bx !"
b0 ~
bx }
bx |
bx {
bx z
bx y
b0 x
bx w
bx v
bx u
bx t
bx s
bx r
bx q
bx p
bx o
b0 n
b0 m
b0 l
b0 k
bx j
bx i
bx h
bx g
0f
xe
xd
xc
xb
0a
x`
x_
x^
x]
0\
x[
xZ
xY
xX
0W
xV
xU
xT
xS
xR
xQ
xP
xO
xN
xM
xL
xK
xJ
xI
xH
xG
xF
xE
xD
xC
xB
xA
x@
x?
bx >
bx =
bx <
bx ;
0:
09
08
07
b0 6
b0 5
b0 4
b0 3
bx 2
bx 1
bx 0
bx /
b0 .
b0 -
b0 ,
b0 +
1*
b0 )
b0 (
b0 '
b0 &
0%
b0 $
b0 #
b0 "
b0 !
$end
#5
0C
0H
0M
0R
0b
0]
0X
0S
0c
0^
0Y
0T
0d
0_
0Z
0U
0e
0`
0[
0V
b0 >
b0 r
b0 w
b0 }
b0 %"
b0 +"
b0 2"
b0 7"
b0 9"
b0 >"
13"
b0 ;"
b0 =
b0 q
b0 v
b0 |
b0 $"
b0 *"
b0 F"
b0 K"
b0 M"
b0 R"
1G"
b0 O"
b0 <
b0 p
b0 u
b0 {
b0 #"
b0 )"
b0 Z"
b0 _"
b0 a"
b0 f"
1["
b0 c"
b0 ;
b0 o
b0 t
b0 z
b0 ""
b0 ("
b0 n"
b0 s"
b0 u"
b0 z"
1o"
b0 w"
b0 8"
b1 5"
b0 6"
b0 /"
b0 :"
b0 ?"
b0 ="
b0 2
b0 0"
b0 <"
01"
b0 L"
b1 I"
b0 J"
b0 C"
b0 N"
b0 S"
b0 Q"
b0 1
b0 D"
b0 P"
0E"
b0 `"
b1 ]"
b0 ^"
b0 W"
b0 b"
b0 g"
b0 e"
b0 0
b0 X"
b0 d"
0Y"
b0 t"
b1 q"
b0 r"
b0 k"
b0 v"
b0 {"
b0 y"
b0 /
b0 l"
b0 x"
0m"
0N
0O
0P
b0 g
b0 s
0Q
0I
0J
0K
b0 h
b0 y
0L
0D
0E
0F
b0 i
b0 !"
0G
0?
0@
0A
b0 j
b0 '"
0B
0W
0\
0a
0f
1%
#10
0%
0*
#15
1f
1a
1\
1W
1%
#20
1."
0%
b1000000000 &
b1000000000 +
b1000000000 -"
b1000000000 4"
b1000000000 @"
#25
b1000000000 >
b1000000000 r
b1000000000 w
b1000000000 }
b1000000000 %"
b1000000000 +"
b1000000000 2"
b1000000000 7"
b1000000000 9"
b1000000000 >"
03"
b10 5"
b1 6"
0W
0\
0a
0f
1%
#30
0%
b100000000 &
b100000000 +
b100000000 -"
b100000000 4"
b100000000 @"
#35
b1 /"
b1 :"
b1 ?"
b11 5"
b10 6"
1f
1a
1\
1W
1%
#40
0%
b100000001 &
b100000001 +
b100000001 -"
b100000001 4"
b100000001 @"
#45
b1 ;"
1S
b100 5"
b11 6"
b1 2
b1 0"
b1 <"
0W
0\
0a
0f
1%
#50
0%
b1100000010 &
b1100000010 +
b1100000010 -"
b1100000010 4"
b1100000010 @"
#55
11"
b10 ;"
1R
b1000000000 $
b1000000000 6
b1000000000 n
b1000000000 x
b1 g
b1 s
1Q
b1 ="
b101 5"
b100 6"
1f
1a
1\
1%
